komposer/__init__.py
komposer/cli.py
komposer/core/__init__.py
komposer/core/base.py
komposer/core/config_map.py
komposer/core/container.py
komposer/core/deployment.py
komposer/core/env_vars.py
komposer/core/extra_manifest.py
komposer/core/ingress.py
komposer/core/service.py
komposer/envsubst.py
komposer/exceptions.py
komposer/types/__init__.py
komposer/types/base.py
komposer/types/cli.py
komposer/types/docker_compose.py
komposer/types/kubernetes.py
komposer/types/ports.py
komposer/utils.py
komposer-0.2.0.dist-info/LICENSE
komposer-0.2.0.dist-info/METADATA
komposer-0.2.0.dist-info/WHEEL
komposer-0.2.0.dist-info/entry_points.txt
komposer-0.2.0.dist-info/RECORD
